README.txt
setup.cfg
setup.py
confluent/__init__.py
confluent/tlv.py
confluent/tlvdata.py
confluent_common.egg-info/PKG-INFO
confluent_common.egg-info/SOURCES.txt
confluent_common.egg-info/dependency_links.txt
confluent_common.egg-info/top_level.txt