Metadata-Version: 1.0
Name: confluent-common
Version: 0.1.2
Summary: common content for confluent client and server
Home-page: http://xcat.sf.net/
Author: Jarrod Johnson
Author-email: jbjohnso@us.ibm.com
License: UNKNOWN
Platform: UNKNOWN
